cenotes_lib/__init__.py
cenotes_lib/crypto.py
cenotes_lib/exceptions.py
cenotes_lib/helpers.py
cenotes_lib-0.2.4.dist-info/DESCRIPTION.rst
cenotes_lib-0.2.4.dist-info/METADATA
cenotes_lib-0.2.4.dist-info/RECORD
cenotes_lib-0.2.4.dist-info/WHEEL
cenotes_lib-0.2.4.dist-info/metadata.json
cenotes_lib-0.2.4.dist-info/top_level.txt
tests/__init__.py
tests/conftest.py
tests/test_crypto.py
tests/test_helpers.py
