Metadata-Version: 2.0
Name: cenotes-lib
Version: 0.2.4
Summary: Cenotes libraries
Home-page: https://github.com/cenotes/cenotes-lib
Author: John Paraskevopoulos
Author-email: ioparaskev@gmail.com
License: GNU General Public License v3
Keywords: cenotes
Platform: UNKNOWN
Classifier: Development Status :: 4 - Beta
Classifier: Intended Audience :: Developers
Classifier: License :: OSI Approved :: GNU General Public License v3 (GPLv3)
Classifier: Natural Language :: English
Classifier: Programming Language :: Python :: 3
Classifier: Programming Language :: Python :: 3.4
Classifier: Programming Language :: Python :: 3.5
Classifier: Programming Language :: Python :: 3.6
Requires-Dist: Click (>=6.0)
Requires-Dist: pynacl (>=1.2.0)
